{
 "edicion": "30ª OMI",
 "clave": 30,
 "year": 2025,
 "num": 3,
 "dia": "Día 1",
 "titulo": "Matriz",
 "judge": "pdf",
 "statement_link": "https://www.olimpiadadeinformatica.org.mx/OMI/OMI/archivos/problemas/omi2025/matriz.pdf",
 "omegaup_alias": null,
 "dmoj_code": null,
 "pdf_url": "https://www.olimpiadadeinformatica.org.mx/OMI/OMI/archivos/problemas/omi2025/matriz.pdf",
 "casos": "https://www.olimpiadadeinformatica.org.mx/OMI/OMI/archivos/problemas/omi2025/matriz.zip",
 "codigos": "https://www.olimpiadadeinformatica.org.mx/OMI/OMI/archivos/problemas/omi2025/omi2025d1p3.cpp",
 "soluciones": null
}
